oncoprinter/__init__.py
oncoprinter/core.py
oncoprinter/preset.py
oncoprinter-0.2.0.dist-info/LICENSE
oncoprinter-0.2.0.dist-info/WHEEL
oncoprinter-0.2.0.dist-info/METADATA
oncoprinter-0.2.0.dist-info/RECORD
